mindstorm/__init__.py
mindstorm/dsmplot.py
mindstorm/glm.py
mindstorm/prsa.py
mindstorm/statplot.py
mindstorm/subjutil.py
mindstorm-0.11.2.data/scripts/apply_clustsim_svc.sh
mindstorm-0.11.2.data/scripts/lsvol
mindstorm-0.11.2.data/scripts/remove_short_runs.py
mindstorm-0.11.2.data/scripts/run_freesurfer.sh
mindstorm-0.11.2.data/scripts/smooth_susan
mindstorm-0.11.2.data/scripts/transform_func2mni.sh
mindstorm-0.11.2.data/scripts/transform_mni2func.sh
mindstorm-0.11.2.data/scripts/zstat_randomise.sh
mindstorm-0.11.2.dist-info/licenses/LICENSE
mindstorm-0.11.2.dist-info/METADATA
mindstorm-0.11.2.dist-info/WHEEL
mindstorm-0.11.2.dist-info/entry_points.txt
mindstorm-0.11.2.dist-info/top_level.txt
mindstorm-0.11.2.dist-info/RECORD
