Metadata-Version: 2.4
Name: mindstorm
Version: 0.11.2
Summary: Mindstorm: Advanced analysis of neuroimaging data
Author-email: Neal W Morton <mortonne@gmail.com>
License:                     GNU GENERAL PUBLIC LICENSE
Project-URL: project, https://github.com/mortonne/mindstorm
Keywords: fmri,psychology,neuroscience,RSA
Classifier: Programming Language :: Python :: 3
Classifier: License :: OSI Approved :: GNU General Public License v3 or later (GPLv3+)
Classifier: Operating System :: OS Independent
Requires-Python: >=3.8
License-File: LICENSE
Requires-Dist: numpy
Requires-Dist: scipy
Requires-Dist: pandas
Requires-Dist: seaborn>=0.13.0
Requires-Dist: pybids
Requires-Dist: nibabel
Requires-Dist: nilearn
Requires-Dist: scikit-learn
Requires-Dist: click
Requires-Dist: nipype
Dynamic: license-file
